[{"label": "EDPR 393", "name": "Special Topics", "prereq": ["EDUC 405"]}, {"label": "EDPR 394", "name": "Special Topics", "prereq": ["EDUC 405"]}, {"label": "EDPR 492", "name": "Special Topics", "prereq": ["EDUC 405"]}, {"label": "EDPR 493", "name": "Special Topics", "prereq": ["EDUC 405"]}, {"label": "EDPR 494", "name": "Special Topics", "prereq": ["EDUC 405"]}, {"label": "EDPR 495", "name": "Special Topics", "prereq": ["EDUC 405"]}, {"label": "EDPR 496", "name": "Special Topics", "prereq": ["EDUC 405"]}, {"label": "EDPR 497", "name": "Special Topics", "prereq": ["EDUC 405"]}, {"label": "EDPR 498", "name": "Special Topics", "prereq": ["EDUC 405"]}, {"label": "EDPR 499", "name": "Special Topics", "prereq": ["EDUC 405"]}]